django_pyodbc_lb-1.11.0.1.dist-info/DESCRIPTION.rst
django_pyodbc_lb-1.11.0.1.dist-info/METADATA
django_pyodbc_lb-1.11.0.1.dist-info/RECORD
django_pyodbc_lb-1.11.0.1.dist-info/WHEEL
django_pyodbc_lb-1.11.0.1.dist-info/metadata.json
django_pyodbc_lb-1.11.0.1.dist-info/top_level.txt
sql_server_lb/__init__.py
sql_server_lb/base.py
