Metadata-Version: 2.0
Name: django-pyodbc-lb
Version: 1.11.0.1
Summary: Django backend for Microsoft SQL Server with load balancer support
Home-page: https://github.com/peterdemin/django-pyodbc-lb
Author: Petr Demin
Author-email: deminp@ncbi.nlm.nih.gov
License: BSD
Keywords: mssql django
Platform: UNKNOWN
Classifier: Development Status :: 4 - Beta
Classifier: License :: OSI Approved :: BSD License
Classifier: Framework :: Django
Classifier: Programming Language :: Python
Classifier: Programming Language :: Python :: 2
Classifier: Programming Language :: Python :: 2.7
Classifier: Programming Language :: Python :: 3
Classifier: Programming Language :: Python :: 3.4
Classifier: Programming Language :: Python :: 3.5
Classifier: Topic :: Internet :: WWW/HTTP
Requires-Dist: Django (<1.12,>=1.11)
Requires-Dist: django-pyodbc-azure (<1.12,>=1.11)
